waylay/services/rules/models/__init__.py
waylay/services/rules/models/actuator_execution_result.py
waylay/services/rules/models/actuator_node.py
waylay/services/rules/models/batch_id_query.py
waylay/services/rules/models/batch_operation.py
waylay/services/rules/models/batch_operation_enqueued.py
waylay/services/rules/models/batch_operation_operation.py
waylay/services/rules/models/batch_operation_operation_action.py
waylay/services/rules/models/batch_operation_result.py
waylay/services/rules/models/batch_query.py
waylay/services/rules/models/batch_task.py
waylay/services/rules/models/batch_task_command.py
waylay/services/rules/models/batch_task_command_all_of_action.py
waylay/services/rules/models/batch_task_entity.py
waylay/services/rules/models/batch_task_query.py
waylay/services/rules/models/batch_task_spec.py
waylay/services/rules/models/batch_update_plugin.py
waylay/services/rules/models/batch_update_properties.py
waylay/services/rules/models/batch_update_properties_all_of_action.py
waylay/services/rules/models/bayesian_graph.py
waylay/services/rules/models/create_task201_response.py
waylay/services/rules/models/create_template201_response.py
waylay/services/rules/models/error_response.py
waylay/services/rules/models/error_with_details_response.py
waylay/services/rules/models/execute_plugs_specification.py
waylay/services/rules/models/execution_trigger.py
waylay/services/rules/models/failure_operation_result_value.py
waylay/services/rules/models/gate_type.py
waylay/services/rules/models/generic_task_settings.py
waylay/services/rules/models/generic_trigger.py
waylay/services/rules/models/get_batch_operation200_response.py
waylay/services/rules/models/get_discovery_template200_response.py
waylay/services/rules/models/get_template200_response.py
waylay/services/rules/models/graph_definition.py
waylay/services/rules/models/list_tasks200_response.py
waylay/services/rules/models/list_tasks_format_parameter.py
waylay_sdk_rules_types-6.12.0.20241025.dist-info/LICENSE.txt
waylay_sdk_rules_types-6.12.0.20241025.dist-info/METADATA
waylay_sdk_rules_types-6.12.0.20241025.dist-info/WHEEL
waylay_sdk_rules_types-6.12.0.20241025.dist-info/top_level.txt
waylay_sdk_rules_types-6.12.0.20241025.dist-info/RECORD
